_CharLS.pyd
CharPyLS-1.0.0.dist-info/DESCRIPTION.rst
CharPyLS-1.0.0.dist-info/METADATA
CharPyLS-1.0.0.dist-info/pydist.json
CharPyLS-1.0.0.dist-info/RECORD
CharPyLS-1.0.0.dist-info/top_level.txt
CharPyLS-1.0.0.dist-info/WHEEL
jpeg_ls/CharLS.py
jpeg_ls/data_io.py
jpeg_ls/define_charls_dll.h
jpeg_ls/example.py
jpeg_ls/_CharLS.cpp
jpeg_ls/_CharLS.pyx
jpeg_ls/__init__.py
