Metadata-Version: 2.0
Name: CharPyLS
Version: 1.0.0
Summary: JPEG-LS for Python via CharLS C++ Library
Home-page: https://github.com/Who8MyLunch/CharPyLS
Author: Pierre V. Villeneuve
Author-email: pierre.villeneuve@gmail.com
License: MIT
Platform: UNKNOWN
